LICENSE
MANIFEST.in
README.rst
setup.cfg
setup.py
linkat/__init__.py
linkat/ffi.py
linkat/linkat.py
linkat.egg-info/PKG-INFO
linkat.egg-info/SOURCES.txt
linkat.egg-info/dependency_links.txt
linkat.egg-info/not-zip-safe
linkat.egg-info/requires.txt
linkat.egg-info/top_level.txt